assets/__init__.py
assets/apps.py
assets/bottle.py
assets/finders.py
assets/manifest.py
assets/middleware.py
assets/storage.py
assets/watcher.py
assets/filters/__init__.py
assets/filters/clojure.py
assets/filters/cssmin.py
assets/filters/sass.py
assets/filters/utils.py
assets/management/__init__.py
assets/management/bottle.py
assets/management/liveserver.py
assets/management/supervisor.py
assets/management/utils.py
assets/management/wsgi_worker.py
assets/management/commands/findmanifests.py
assets/management/commands/listfilters.py
assets/management/commands/liveserver.py
assets/management/commands/reload.py
assets/management/commands/restart.py
assets/static/manifest.json
assets/static/assets/js/livereload.js
assets/templatetags/asset.py
assets/tests/__init__.py
assets/tests/settings.py
assets/tests/urls.py
assets/tests/static/manifest/manifest.json
assets/tests/unittests/test_manifesttree.py
django_assets_livereload-0.2.0.dist-info/DESCRIPTION.rst
django_assets_livereload-0.2.0.dist-info/METADATA
django_assets_livereload-0.2.0.dist-info/RECORD
django_assets_livereload-0.2.0.dist-info/WHEEL
django_assets_livereload-0.2.0.dist-info/metadata.json
django_assets_livereload-0.2.0.dist-info/pbr.json
django_assets_livereload-0.2.0.dist-info/top_level.txt
