Metadata-Version: 2.0
Name: django-assets-livereload
Version: 0.2.0
Summary: Enhanced staticfiles django app.
Home-page: https://gitlab.com/Verner/django-assets-livereload
Author: Jonathan L. Verner
Author-email: jonathan@temno.eu
License: MIT License
Keywords: django
Requires-Dist: Django (>=1.9.12)
Requires-Dist: gevent (>=1.2.1)
Requires-Dist: gevent-websocket (>=0.10.1)
Requires-Dist: inotify (==0.2.8)
